cs/timeseries.py
cs.timeseries-20240316.dist-info/METADATA
cs.timeseries-20240316.dist-info/WHEEL
cs.timeseries-20240316.dist-info/entry_points.txt
cs.timeseries-20240316.dist-info/top_level.txt
cs.timeseries-20240316.dist-info/RECORD
