Metadata-Version: 2.1
Name: cs.timeseries
Version: 20240316
Summary: Efficient portable machine native columnar file storage of time series data for double float and signed 64-bit integers.
Author-email: Cameron Simpson <cs@cskk.id.au>
License: GNU General Public License v3 or later (GPLv3+)
Project-URL: URL, https://bitbucket.org/cameron_simpson/css/commits/all
Keywords: python3
Platform: UNKNOWN
Classifier: Development Status :: 3 - Alpha
Classifier: Programming Language :: Python :: 3
Classifier: Intended Audience :: Developers
Classifier: Operating System :: OS Independent
Classifier: Topic :: Software Development :: Libraries :: Python Modules
Classifier: License :: OSI Approved :: GNU General Public License v3 or later (GPLv3+)
Requires-Dist: arrow
Requires-Dist: cs.binary >=20240201
Requires-Dist: cs.buffer >=20240316
Requires-Dist: cs.cmdutils >=20240316
Requires-Dist: cs.configutils >=20220430
Requires-Dist: cs.context >=20240212.1
Requires-Dist: cs.csvutils >=20220606
Requires-Dist: cs.deco >=20221106.1
Requires-Dist: cs.fileutils >=20210731
Requires-Dist: cs.fs >=20240316
Requires-Dist: cs.fstags >=20240316
Requires-Dist: cs.lex >=20240211
Requires-Dist: cs.logutils >=20230212
Requires-Dist: cs.mappings >=20231129
Requires-Dist: cs.mplutils >=20230407
Requires-Dist: cs.pfx >=20230604
Requires-Dist: cs.progress >=20230401
Requires-Dist: cs.py.modules >=20220606
Requires-Dist: cs.resources >=20240316
Requires-Dist: cs.result >=20240305
Requires-Dist: cs.upd >=20240216
Requires-Dist: icontract
Requires-Dist: matplotlib
Requires-Dist: numpy
Requires-Dist: python-dateutil
Requires-Dist: typeguard
